CHANGES.txt
README.txt
buildout.cfg
setup.py
bootstrap/bootstrap.py
src/ulif/__init__.py
src/ulif.plone.testsetup.egg-info/PKG-INFO
src/ulif.plone.testsetup.egg-info/SOURCES.txt
src/ulif.plone.testsetup.egg-info/dependency_links.txt
src/ulif.plone.testsetup.egg-info/namespace_packages.txt
src/ulif.plone.testsetup.egg-info/not-zip-safe
src/ulif.plone.testsetup.egg-info/requires.txt
src/ulif.plone.testsetup.egg-info/top_level.txt
src/ulif/plone/__init__.py
src/ulif/plone/testsetup/README.txt
src/ulif/plone/testsetup/__init__.py
src/ulif/plone/testsetup/plonetesting.py
src/ulif/plone/testsetup/tests/__init__.py
src/ulif/plone/testsetup/tests/test_setup.py
src/ulif/plone/testsetup/tests/cave/__init__.py
src/ulif/plone/testsetup/tests/cave/configure.zcml
src/ulif/plone/testsetup/tests/cave/functionaltest.txt
src/ulif/plone/testsetup/tests/cave/sampletestsetup.py
src/ulif/plone/testsetup/tests/cave/untittest.txt
src/ulif/plone/testsetup/tests/cave/profiles/default/properties.xml