Metadata-Version: 1.0
Name: ulif.plone.testsetup
Version: 0.1.2
Summary: Easier test setup for Plone 3 projects.
Home-page: https://cheeseshop.python.org/pypi/ulif.plone.testsetup
Author: Uli Fouquet
Author-email: uli@gnufix.de
License: ZPL 2.1
Keywords: plone3 plone zope test unittest doctest testsetup
Platform: UNKNOWN
Classifier: Development Status :: 3 - Alpha
Classifier: Environment :: Web Environment
Classifier: Intended Audience :: Developers
Classifier: License :: OSI Approved :: GNU General Public License (GPL)
Classifier: Programming Language :: Python
Classifier: Operating System :: OS Independent
Classifier: Framework :: Plone
Classifier: Topic :: Software Development :: Libraries :: Python Modules
